README.md
license.txt
setup.py
pro_video_tools_pilot.egg-info/PKG-INFO
pro_video_tools_pilot.egg-info/SOURCES.txt
pro_video_tools_pilot.egg-info/dependency_links.txt
pro_video_tools_pilot.egg-info/top_level.txt
pro_video_tools_piloto/__init__.py
pro_video_tools_piloto/camera.py
pro_video_tools_piloto/video.py