Metadata-Version: 2.1
Name: pro-video-tools-pilot
Version: 1.0
Summary: Este pacote irá fornecer ferramentas de processamento de vídeo
Author: Ciroc_1995
Author-email: cicero.cordeiro1995@gmail.com
Keywords: camera,video,processamento
License-File: license.txt
